tmia_analyzer/__init__.py
tmia_analyzer/analyzers.py
tmia_analyzer-0.0.6.dist-info/LICENSE
tmia_analyzer-0.0.6.dist-info/METADATA
tmia_analyzer-0.0.6.dist-info/WHEEL
tmia_analyzer-0.0.6.dist-info/top_level.txt
tmia_analyzer-0.0.6.dist-info/RECORD
