Metadata-Version: 2.1
Name: tmia-analyzer
Version: 0.0.6
Summary: A simple python package to handle common requests for data for Whole Foods Market's Team Member Insights team.
Home-page: https://github.com/wfm-bdaum/wfm-tmia-analyzer
Author: Brian Daum
Author-email: brian.daum@wholefoods.com
License: UNKNOWN
Project-URL: Bug Tracker, https://github.com/wfm-bdaum/wfm-tmia-analyzer/issues
Platform: UNKNOWN
Classifier: Programming Language :: Python :: 3
Classifier: License :: OSI Approved :: MIT License
Classifier: Operating System :: OS Independent
Requires-Python: >=3.6
License-File: LICENSE
